[

  {
    "id": "smart-home-systems",
    "isHomeFeatured": true,
    "logo": "/src/assets/smart_home/smart_home-logo.png",
    "logoText": "/src/assets/smart_home/smart_home-logo-txt.png",
    "logoIcon": "/src/assets/smart_home/smart_home-logo-icon.png",
    "title": "Smart Home Systems",
    "description": "Advanced home automation for modern living",
    "videoUrl": "/videos/smart_home_systems.mp4",
    "icon": "Wifi",
    "items": [
      "Smart Lighting",
      "Smart Locks",
      "Voice Control",
      "Home Theater",
      "HVAC Automation"
    ],
    "color": "text-primary"
  },
    {
    "id": "solar-energy",
    "isHomeFeatured": true,
    "logo": "/src/assets/solar/solar-logo.png",
    "logoText": "/src/assets/solar/solar-logo-txt.png",
    "logoIcon": "/src/assets/solar/solar-logo-icon.png",
    "title": "Solar Energy",
    "description": "Sustainable power solutions for your future",
    "videoUrl": "/videos/solar_energy.mp4",
    "icon": "Leaf",
    "items": [
      "Solar Panel Installation",
      "On/Off/Hybrid/Pumping Grid Systems",
      "Battery Storage",
      "EPC & Maintenance"
    ],
    "color": "text-success"
  },
  {
    "id": "hvac-chiller",
    "isHomeFeatured": true,
    "logo": "/src/assets/hvac/hvac-logo.png",
    "logoText": "/src/assets/hvac/hvac-logo-txt.png",
    "logoIcon": "/src/assets/hvac/hvac-logo-icon.png",
    "title": "HVAC & Chiller",
    "description": "Climate control and air quality solutions",
    "videoUrl": "src/videos/hvac_chiller.mp4",
    "icon": "AirVent",
    "items": [
      "Ducting Fabrication",
      "Chillers",
      "Air Handling Units",
      "Maintenance"
    ],
    "color": "text-info"
  },
  {
    "id": "plumbing",
    "isHomeFeatured": false,
    "logo": "/src/assets/plumbing/plumbing-logo.png",
    "logoText": "/src/assets/plumbing/plumbing-logo-txt.png",
    "logoIcon": "/src/assets/plumbing/plumbing-logo-icon.png",
    "title": "Plumbing",
    "description": "Complete water and drainage systems",
    "videoUrl": "/videos/plumbing.mp4",
    "icon": "Droplets",
    "items": [
      "Water & Drainage Systems",
      "Heaters",
      "Solar Hot Water",
      "Leak Detection"
    ],
    "color": "text-primary"
  },
  {
    "id": "fire-fighting",
    "isHomeFeatured": true,
    "logo": "/src/assets/fire/fire-logo.png",
    "logoText": "/src/assets/fire/fire-logo-txt.png",
    "logoIcon": "/src/assets/fire/fire-logo-icon.png",
    "title": "Fire Fighting",
    "description": "Comprehensive fire safety solutions",
    "videoUrl": "/videos/fire_fighting.mp4",
    "icon": "FireExtinguisher",
    "items": [
      "Fire Suppression Systems",
      "Fire Alarms",
      "Emergency Lighting",
      "Sprinkler Systems"
    ],
    "color": "text-danger"
  },
  {
    "id": "electrical",
    "isHomeFeatured": true,
    "logo": "/src/assets/electrical/electrical-logo.png",
    "logoText": "/src/assets/electrical/electrical-logo-txt.png",
    "logoIcon": "/src/assets/electrical/electrical-logo-icon.png",
    "title": "Electrical",
    "description": "Professional electrical installations",
    "videoUrl": "/videos/electrical.mp4",
    "icon": "Zap",
    "items": [
      "Power Distribution",
      "Panels",
      "Lighting",
      "Backup Systems",
      "Earthing"
    ],
    "color": "text-warning"
  },
  {
    "id": "network-security",
    "isHomeFeatured": true,
    "logo": "/src/assets/network-security/network-security-logo.png",
    "logoText": "/src/assets/network/network-logo-txt.png",
    "logoIcon": "/src/assets/network/network-logo-icon.png",
    "title": "Network & Security",
    "description": "Modern IT infrastructure solutions",
    "videoUrl": "/videos/network_security.mp4",
    "icon": "Network",
    "items": [
      "Structured Cabling",
      "Wi-Fi",
      "CCTV",
      "PAVA Public Addres and Voice Alarm",
      "Access Control",
      "Data Rack Setup"
    ],
    "color": "text-secondary"
  }
]